addteam/__init__.py
addteam/bootstrap_repo.py
addteam/cli.py
addteam/py.typed
addteam-0.8.6.dist-info/licenses/LICENSE
addteam-0.8.6.dist-info/METADATA
addteam-0.8.6.dist-info/WHEEL
addteam-0.8.6.dist-info/entry_points.txt
addteam-0.8.6.dist-info/top_level.txt
addteam-0.8.6.dist-info/RECORD
