Metadata-Version: 2.4
Name: addteam
Version: 0.8.6
Summary: One-command collaborator management for GitHub repos with GitOps support.
Author-email: Michael Jabbour <michael@jabbour.me>
License-Expression: MIT
Project-URL: Homepage, https://github.com/michaeljabbour/addteam
Project-URL: Repository, https://github.com/michaeljabbour/addteam
Project-URL: Issues, https://github.com/michaeljabbour/addteam/issues
Keywords: github,collaborators,team,access,gitops,automation
Classifier: Development Status :: 4 - Beta
Classifier: Environment :: Console
Classifier: Intended Audience :: Developers
Classifier: Operating System :: OS Independent
Classifier: Programming Language :: Python :: 3
Classifier: Programming Language :: Python :: 3.10
Classifier: Programming Language :: Python :: 3.11
Classifier: Programming Language :: Python :: 3.12
Classifier: Topic :: Software Development :: Version Control :: Git
Requires-Python: >=3.10
License-File: LICENSE
Requires-Dist: httpx
Requires-Dist: rich
Requires-Dist: pyyaml>=6.0
Provides-Extra: dev
Requires-Dist: pytest>=7.0; extra == "dev"
Requires-Dist: ruff>=0.1.0; extra == "dev"
Dynamic: license-file
